{
  "items": [
    {
      "id": "integrations-apps",
      "title": "Integraciones",
      "description": "Acelere su trabajo con estas herramientas adicionales.",
      "url": "",
      "children": [
        {
          "id": "apps-unstructured",
          "title": "Aproveche más tipos de datos con Unstructured",
          "description": "Automatice la ingesta y transformación de datos a gran escala en el almacén de vectores.",
          "icon": "unstructured",
          "url": "",
          "childrenUrl": "https://unstructured.io"
        },
        {
          "id": "apps-gitea",
          "title": "Versione su código Git con Gitea",
          "description": "Use Gitea para control de versiones y persistencia de sus proyectos.",
          "icon": "gitea",
          "url": "",
          "childrenUrl": "/one-td/git/"
        },
        {
          "id": "apps-airflow",
          "title": "Cree flujos de trabajo con Airflow",
          "description": "Configure y programe canalizaciones de proyectos con esta herramienta de orquestación.",
          "icon": "airflow",
          "url": "",
          "childrenUrl": "/one-td/airflow/login/PingIDP"
        },
        {
          "id": "apps-devpi",
          "title": "Administre paquetes de Python con devpi",
          "description": "Usa devpi para administrar sus paquetes privados de Python desde PyPI.",
          "icon": "devpi",
          "url": "",
          "childrenUrl": "/one-td/pypi"
        }
      ]
    },
    {
      "id": "integrations-learnmore",
      "title": "Más información",
      "description": "Consulte la documentación y los recursos de aprendizaje.",
      "url": "",
      "children": [
        {
          "id": "learn-unstructured",
          "title": "Transforme los datos con Unstructured",
          "description": "Aprenda cómo convertir sus documentos desestructurados en datos estructurados, listos para IA a escala.",
          "icon": "",
          "url": "",
          "childrenUrl": "https://docs.unstructured.io/welcome"
        },
        {
          "id": "learn-gitea",
          "title": "Versione su código Git con Gitea",
          "description": "Aloje usted mismo sus repositorios de Git para revisiones de código, colaboración, registro de paquetes y CI/CD.",
          "icon": "",
          "url": "",
          "childrenUrl": "https://docs.gitea.com/"
        },
        {
          "id": "learn-createairflow",
          "title": "Cree flujos de trabajo con Airflow",
          "description": "Configure y programe flujos de trabajo usando scripts de notebook como componentes.",
          "icon": "",
          "url": "",
          "childrenUrl": "https://airflow.apache.org/docs/apache-airflow/stable/index.html"
        },
        {
          "id": "learn-runairflow",
          "title": "Ejecute flujos de trabajo de Airflow con ModelOps",
          "description": "Acelere el proceso integral de desarrollo, despliegue y administración de modelos.",
          "icon": "",
          "url": "",
          "childrenUrl": "https://developers.teradata.com/quickstarts/analyze-data/execute-airflow-workflows-with-clearscape-analytics-modelops-model-factory-solution/"
        },
        {
          "id": "learn-devpi",
          "title": "Administre paquetes de Python con devpi",
          "description": "Impulse el empaquetado, la prueba y el lanzamiento de actividades con Python.",
          "icon": "",
          "url": "",
          "childrenUrl": "https://devpi.net/docs/devpi/devpi/stable/%2Bd/index.html"
        }
      ]
    }
  ]
}