{  "items":[
    { 
       "id":"sbt1640280496980", 
       "title":"Environments", 
       "description":"Load data, run queries, and more.", 
       "url":"Vantage/sbt1640280496980.md", 
       "children":[
          { 
             "id":"nmr1658424425362", 
             "title":"Environment key concepts", 
             "description":"Environment description, components, and characteristics", 
             "url":"Vantage/nmr1658424425362.md"
             }
          , 
          { 
             "id":"qiv1640281527006", 
             "title":"Create an environment", 
             "description":"Considerations for creating an environment", 
             "url":"Vantage/qiv1640281527006.md"
             }
          , 
          { 
             "id":"laq1640280582810", 
             "title":"Configure connection settings", 
             "description":"Considerations for using Internet or Private link", 
             "url":"Vantage/laq1640280582810.md"
             }

          ]

       }
    , 
    { 
       "id":"mqu1640280532737", 
       "title":"Compute groups", 
       "description":"Create, view, and manage Compute groups. ", 
       "url":"Vantage/mqu1640280532737.md", 
       "children":[
          { 
             "id":"ixo1658772101054", 
             "title":"Compute group key concepts", 
             "description":"Compute group description, components, and characteristics", 
             "url":"Vantage/ixo1658772101054.md"
             }
          , 
          { 
             "id":"xrr1658772541186", 
             "title":"Create a compute group", 
             "description":"Considerations for creating a Compute group", 
             "url":"Vantage/xrr1658772541186.md", 
             "children":[
                { 
                   "id":"dvl1640281718303", 
                   "title":"Profiles", 
                   "description":"Profile description and characteristics", 
                   "url":"Vantage/dvl1640281718303.md"
                   }
                , 
                { 
                   "id":"wdz1640281743091", 
                   "title":"User roles and access", 
                   "description":"User roles and access descriptions and characteristics", 
                   "url":"Vantage/wdz1640281743091.md"
                   }

                ]

             }
          , 
          { 
             "id":"sqv1658772608902", 
             "title":"Manage compute groups", 
             "description":"Considerations for viewing and editing compute groups", 
             "url":"Vantage/sqv1658772608902.md"
             }

          ]

       }
    , 
    { 
       "id":"xbg1640280430669", 
       "title":"Editor", 
       "description":"Write and run SQL queries.", 
       "url":"Vantage/xbg1640280430669.md", 
       "children":[
          { 
             "id":"xti1659380438762", 
             "title":"Editor key concepts", 
             "description":"Editor description, components, and characteristics", 
             "url":"Vantage/xti1659380438762.md"
             }
          , 
          { 
             "id":"juo1640281123239", 
             "title":"Add a connection", 
             "description":"Considerations for connecting to an account", 
             "url":"Vantage/juo1640281123239.md"
             }
          , 
          { 
             "id":"dgd1640281158386", 
             "title":"Create and run a SQL statement or script", 
             "description":"Considerations for running SQL", 
             "url":"Vantage/dgd1640281158386.md"
             }

          ]

       }
    , 
    { 
       "id":"apw1640280478763", 
       "title":"Organization", 
       "description":"View company information and manage administrators.", 
       "url":"Vantage/apw1640280478763.md", 
       "children":[
          { 
             "id":"bbi1659385111806", 
             "title":"Organization Key Concepts", 
             "description":"Organization description, components, and characteristics", 
             "url":"Vantage/bbi1659385111806.md"
             }
          , 
          { 
             "id":"hrv1640281410572", 
             "title":"Manage organization admins", 
             "description":"Considerations for managing organization admins", 
             "url":"Vantage/hrv1640281410572.md"
             }

          ]

       }
    , 
    { 
       "id":"ajr1640280560519", 
       "title":"Queries", 
       "description":"View current or completed queries on the account.", 
       "url":"Vantage/ajr1640280560519.md", 
       "children":[
          { 
             "id":"aow1659389241176", 
             "title":"Queries key concepts", 
             "description":"Queries description, components, and characteristics", 
             "url":"Vantage/aow1659389241176.md"
             }
          , 
          { 
             "id":"fcd1640281818081", 
             "title":"Load current and completed queries", 
             "description":"Considerations for loading queries", 
             "url":"Vantage/fcd1640281818081.md"
             }

          ]

       }
    , 
    { 
       "id":"arh1640280750562", 
       "title":"Users", 
       "description":"View and manage users, including roles and permissions.", 
       "url":"Vantage/arh1640280750562.md", 
       "children":[
          { 
             "id":"hnc1659392455718", 
             "title":"User key concepts", 
             "description":"User description, components, and characteristics", 
             "url":"Vantage/hnc1659392455718.md"
             }
          , 
          { 
             "id":"wxe1659392685092", 
             "title":"Manage users", 
             "description":"Considerations for viewing, adding, and editing users", 
             "url":"Vantage/wxe1659392685092.md"
             }

          ]

       }
    , 
    { 
       "id":"bkm1640280721917", 
       "title":"Use cases", 
       "description":"Run use cases to explore VantageCloud Lake capabilities.", 
       "url":"Vantage/bkm1640280721917.md"
       }

    ]

 }
